phantom/action_handler/__init__.py
phantom_appdev/action_handler/__init__.py
phantom_dev/action_handler/__init__.py
phantom_action_handler-0.0.1a9.dist-info/METADATA
phantom_action_handler-0.0.1a9.dist-info/WHEEL
phantom_action_handler-0.0.1a9.dist-info/top_level.txt
phantom_action_handler-0.0.1a9.dist-info/RECORD
