Metadata-Version: 2.1
Name: phantom-action-handler
Version: 0.0.1a9
Summary: Utilities to simplify Phantom app development
Home-page: https://gitlab.com/phantom6/phantom-action-handler
Author: David Finn
Author-email: dfinn@splunk.com
License: UNKNOWN
Platform: UNKNOWN
Requires-Python: >=3.6
